pulumi_kong/__init__.py
pulumi_kong/_inputs.py
pulumi_kong/_utilities.py
pulumi_kong/certificate.py
pulumi_kong/consumer.py
pulumi_kong/consumer_acl.py
pulumi_kong/consumer_basic_auth.py
pulumi_kong/consumer_jwt_auth.py
pulumi_kong/consumer_key_auth.py
pulumi_kong/consumer_oauth2.py
pulumi_kong/outputs.py
pulumi_kong/plugin.py
pulumi_kong/provider.py
pulumi_kong/pulumi-plugin.json
pulumi_kong/py.typed
pulumi_kong/route.py
pulumi_kong/service.py
pulumi_kong/target.py
pulumi_kong/upstream.py
pulumi_kong/config/__init__.py
pulumi_kong/config/__init__.pyi
pulumi_kong/config/vars.py
pulumi_kong-4.5.12.dist-info/METADATA
pulumi_kong-4.5.12.dist-info/WHEEL
pulumi_kong-4.5.12.dist-info/top_level.txt
pulumi_kong-4.5.12.dist-info/RECORD
